llm_ie/__init__.py
llm_ie/asset/PromptEditor_prompts/chat.txt
llm_ie/asset/PromptEditor_prompts/comment.txt
llm_ie/asset/PromptEditor_prompts/rewrite.txt
llm_ie/asset/PromptEditor_prompts/system.txt
llm_ie/asset/default_prompts/BasicReviewFrameExtractor_addition_review_prompt.txt
llm_ie/asset/default_prompts/BasicReviewFrameExtractor_revision_review_prompt.txt
llm_ie/asset/default_prompts/ReviewFrameExtractor_addition_review_prompt.txt
llm_ie/asset/default_prompts/ReviewFrameExtractor_revision_review_prompt.txt
llm_ie/asset/default_prompts/SentenceReviewFrameExtractor_addition_review_prompt.txt
llm_ie/asset/default_prompts/SentenceReviewFrameExtractor_revision_review_prompt.txt
llm_ie/asset/prompt_guide/AttributeExtractor_prompt_guide.txt
llm_ie/asset/prompt_guide/BasicFrameExtractor_prompt_guide.txt
llm_ie/asset/prompt_guide/BasicReviewFrameExtractor_prompt_guide.txt
llm_ie/asset/prompt_guide/BinaryRelationExtractor_prompt_guide.txt
llm_ie/asset/prompt_guide/DirectFrameExtractor_prompt_guide.txt
llm_ie/asset/prompt_guide/MultiClassRelationExtractor_prompt_guide.txt
llm_ie/asset/prompt_guide/ReviewFrameExtractor_prompt_guide.txt
llm_ie/asset/prompt_guide/SentenceFrameExtractor_prompt_guide.txt
llm_ie/asset/prompt_guide/SentenceReviewFrameExtractor_prompt_guide.txt
llm_ie/chunkers.py
llm_ie/data_types.py
llm_ie/engines.py
llm_ie/extractors.py
llm_ie/prompt_editor.py
llm_ie-1.2.1.dist-info/METADATA
llm_ie-1.2.1.dist-info/WHEEL
llm_ie-1.2.1.dist-info/RECORD
